{
    "dex number": "024",
    "pokemon name": "Arbok",
    "types": [
        "veneno"
    ],
    "abilities": [
        "Intimidación",
        "Mudar"
    ],
    "hidden abilities": [
        "Nerviosismo"
    ],
    "stats": {
        "hp": 60,
        "atk": 85,
        "def": 69,
        "atk esp": 65,
        "def esp": 79,
        "speed": 80
    },
    "location": {
        "Amarillo": [
            "Intercambiar: de Pokémon Rojo o Pokémon Oro, Plata y Cristal"
        ],
        "Oro": [
            "Evolucionar: a Ekans (Nivel 22)"
        ],
        "Plata": [
            "Salvaje: Rutas 3, 4, 26 y 27.",
            "Evolucionar: a Ekans (Nivel 22)"
        ],
        "Cristal": [
            "Salvaje, mañana y día: Rutas 3, 4, 26, 27, 28, 42, Monte Plateado.",
            "Evolucionar: a Ekans (Nivel 22)"
        ],
        "Rubí": [
            "Intercambiar: de Pokémon Rojo Fuego"
        ],
        "Zafiro": [
            "Intercambiar: de Pokémon Rojo Fuego"
        ],
        "Esmeralda": [
            "Intercambiar: de Pokémon Rojo Fuego"
        ],
        "Rojo Fuego": [
            "Salvaje: Rutas 23, Calle Victoria.",
            "Evolucionar: a Ekans (Nivel 22)"
        ],
        "Verde Hoja": [
            "Intercambiar: de Pokémon Rojo Fuego"
        ],
        "Diamante": [
            "Salvaje: Gran Pantano (con Pokémon Rojo Fuego insertado)",
            "Evolucionar: a Ekans (Nivel 22)",
            "Parque Compi: Zona boscosa."
        ],
        "Perla": [
            "Salvaje: Gran Pantano (con Pokémon Rojo Fuego insertado)",
            "Evolucionar: a Ekans (Nivel 22)",
            "Parque Compi: Zona boscosa."
        ],
        "Platino": [
            "Salvaje: Gran Pantano (con Pokémon Rojo Fuego insertado)",
            "Evolucionar: a Ekans (Nivel 22)",
            "Parque Compi: Zona boscosa."
        ],
        "Oro HeartGold": [
            "Salvaje: Zona Safari (Albufera).",
            "Evolucionar: a Ekans (Nivel 22)",
            "Parque Compi: Zona boscosa."
        ],
        "Plata SoulSilver": [
            "Salvaje: Rutas 3, 4, 26, 27 y Zona Safari (Albufera).",
            "Evolucionar: a Ekans (Nivel 22)",
            "Parque Compi: Zona boscosa."
        ],
        "Negro": [
            "Dream World: Con la habilidad Nerviosismo.",
            "PokéTransfer: Transferir desde Pokémon Diamante, Perla, Platino, Oro HeartGold o Plata SoulSilver.",
            "Evolucionar: a Ekans (Nivel 22)"
        ],
        "Blanco": [
            "Dream World: Con la habilidad Nerviosismo.",
            "PokéTransfer: Transferir desde Pokémon Diamante, Perla, Platino, Oro HeartGold o Plata SoulSilver.",
            "Evolucionar: a Ekans (Nivel 22)"
        ],
        "Negro 2": [
            "Dream World: Con la habilidad Nerviosismo.",
            "PokéTransfer: Transferir desde Pokémon Diamante, Perla, Platino, Oro HeartGold o Plata SoulSilver.",
            "Evolucionar: a Ekans (Nivel 22)"
        ],
        "Blanco 2": [
            "Dream World: Con la habilidad Nerviosismo.",
            "PokéTransfer: Transferir desde Pokémon Diamante, Perla, Platino, Oro HeartGold o Plata SoulSilver.",
            "Evolucionar: a Ekans (Nivel 22)"
        ],
        "Pokémon X": [
            "Salvaje: Ruta 19 (Horda).",
            "Evolucionar: a Ekans (Nivel 22)."
        ],
        "Pokémon Y": [
            "Salvaje: Ruta 19 (Horda).",
            "Evolucionar: a Ekans (Nivel 22)."
        ],
        "Rubí Omega": [
            "Intercambiar: de Pokémon X o Y"
        ],
        "Zafiro Alfa": [
            "Intercambiar: de Pokémon X o Y"
        ],
        "Sol": [
            "Banco de Pokémon: Transferir desde videojuegos anteriores."
        ],
        "Luna": [
            "Banco de Pokémon: Transferir desde videojuegos anteriores."
        ],
        "Ultrasol": [
            "Intercambiar: por Trumbeak en el centro Pokémon de la ruta 8.",
            "Evolucionar: a Ekans (Nivel 22)."
        ],
        "Ultraluna": [
            "Intercambiar: por Trumbeak en el centro Pokémon de la ruta 8.",
            "Evolucionar: a Ekans (Nivel 22)."
        ],
        "Espada": [
            "Arbok no se puede conseguir en este videojuego."
        ],
        "Escudo": [
            "Arbok no se puede conseguir en este videojuego."
        ],
        "Diamante Brillante": [
            "Evolucionar: a Ekans (Nivel 22)"
        ],
        "Perla Reluciente": [
            "Intercambiar: de Pokémon Diamante Brillante"
        ],
        "Leyendas: Arceus": [
            "Arbok no se puede conseguir en este videojuego."
        ]
    },
    "pokedex": {
        "RojoAzul": "Se dice que las feroces señales de alerta de su panza difieren de un área a otra.",
        "Amarillo": "Los espantosos dibujos de su piel han sido estudiados. Seis variaciones han sido confirmadas.",
        "Oro": "Paralizando a su presa con los dibujos de su piel, apresa y envenena a la asustada víctima.",
        "Plata": "De naturaleza muy vengativa, no cejará en la persecución. Irá tras su presa, no importa dónde.",
        "Cristal": "Para intimidar a sus enemigos, hincha el pecho y echa aire por la boca emitiendo sonidos.",
        "Rubí": "Este Pokémon es tremendamente fuerte, puede oprimir cualquier cosa con su cuerpo y hasta es capaz de estrujar un barril de acero. Una vez que Arbok se enrosca a su víctima, no hay forma de escapar de su asfixiante abrazo.",
        "Zafiro": "Este Pokémon es tremendamente fuerte, puede oprimir cualquier cosa con su cuerpo y hasta es capaz de estrujar un barril de acero. Una vez que Arbok se enrosca a su víctima, no hay forma de escapar de su asfixiante abrazo.",
        "Esmeralda": "Es tremendamente fuerte y puede oprimir cualquier cosa con su cuerpo, aplastando incluso barriles de acero. Una vez atrapa a su víctima, no hay forma de escapar.",
        "Rojo Fuego": "El dibujo que tiene en la panza aterroriza. Los rivales más débiles salen huyendo al verlo.",
        "Verde Hoja": "Se dice que las feroces señales de alerta de la panza difieren de un área a otra.",
        "Diamante": "Arbok intimida a sus presas con el dibujo de su panza y luego las asfixia con su cuerpo.",
        "Perla": "Arbok intimida a sus presas con el dibujo de su panza y luego las asfixia con su cuerpo.",
        "Platino": "Arbok intimida a sus presas con el dibujo de su panza y luego las asfixia con su cuerpo.",
        "Oro HeartGold": "Paralizando a su presa con los dibujos de su piel, apresa y envenena a la asustada víctima.",
        "Plata SoulSilver": "De naturaleza muy vengativa, no cejará en la persecución. Irá tras su presa, no importa adónde.",
        "Negro": "Arbok intimida a sus presas con el dibujo de su panza y luego las asfixia con su cuerpo.",
        "Blanco": "Arbok intimida a sus presas con el dibujo de su panza y luego las asfixia con su cuerpo.",
        "Negro 2": "Arbok intimida a sus presas con el dibujo de su panza y luego las asfixia con su cuerpo.",
        "Blanco 2": "Arbok intimida a sus presas con el dibujo de su panza y luego las asfixia con su cuerpo.",
        "Pokémon X": "El dibujo que tiene en la panza aterroriza. Los rivales más débiles salen huyendo al verlo.",
        "Pokémon Y": "Para intimidar a sus enemigos, hincha el pecho y echa aire por la boca emitiendo sonidos.",
        "Rubí Omega": "Este Pokémon es tremendamente fuerte, puede oprimir cualquier cosa con su cuerpo y hasta es capaz de estrujar un barril de acero. Una vez que Arbok se enrosca a su víctima, no hay forma de escapar de su asfixiante abrazo.",
        "Zafiro Alfa": "Este Pokémon es tremendamente fuerte, puede oprimir cualquier cosa con su cuerpo y hasta es capaz de estrujar un barril de acero. Una vez que Arbok se enrosca a su víctima, no hay forma de escapar de su asfixiante abrazo.",
        "Sol": "No hay entrada de este Pokémon en la Pokédex de Pokémon Sol.",
        "Luna": "No hay entrada de este Pokémon en la Pokédex de Pokémon Luna.",
        "Ultrasol": "Recientes estudios han llegado a identificar hasta una veintena de patrones distintos que puede presentar el motivo de su cuello.",
        "Ultraluna": "Tras confundir a su presa con el motivo de su cuerpo, se enrosca a su alrededor y la aferra, a la espera de que su pulso se detenga.",
        "Let's Go Pikachu!Let's Go Eevee!": "Se han llegado a identificar hasta seis variaciones distintas de los espeluznantes dibujos de su piel.",
        "Espada": "Este Pokémon no se puede conseguir en Pokémon Espada.",
        "Escudo": "Este Pokémon no se puede conseguir en Pokémon Escudo.",
        "Diamante Brillante": "Intimida a sus presas con el dibujo de su vientre y, una vez paralizadas por el miedo, se enrosca a su alrededor y las asfixia.",
        "Perla Reluciente": "Intimida a sus presas con el dibujo de su vientre y, una vez paralizadas por el miedo, se enrosca a su alrededor y las asfixia.",
        "Leyendas: Arceus": "Este Pokémon no se puede conseguir en Leyendas Pokémon: Arceus."
    },
    "evolution": [
        [
            "Ekans",
            "Nivel 22",
            "Arbok"
        ]
    ]
}