{
    "dex number": "056",
    "pokemon name": "Mankey",
    "types": [
        "lucha"
    ],
    "abilities": [
        "Espíritu vital",
        "Irascible"
    ],
    "hidden abilities": [
        "Competitivo"
    ],
    "stats": {
        "hp": 40,
        "atk": 80,
        "def": 35,
        "atk esp": 35,
        "def esp": 45,
        "speed": 70
    },
    "location": {
        "Amarillo": [
            "Salvaje: Rutas 3, 4, 22, 23."
        ],
        "Oro": [
            "Salvaje: Ruta 9 y Ruta 42."
        ],
        "Plata": [
            "Intercambiar: de Pokémon Rojo, Pokémon Amarillo o Pokémon Oro"
        ],
        "Cristal": [
            "Intercambiar: de Pokémon Rojo, Pokémon Amarillo o Pokémon Oro"
        ],
        "Rubí": [
            "Intercambiar: de Pokémon Rojo Fuego y Verde Hoja."
        ],
        "Zafiro": [
            "Intercambiar: de Pokémon Rojo Fuego y Verde Hoja."
        ],
        "Esmeralda": [
            "Intercambiar: de Pokémon Rojo Fuego y Verde Hoja."
        ],
        "Rojo Fuego": [
            "Salvaje: Rutas 3, 4, 22, 23 y Túnel Roca."
        ],
        "Verde Hoja": [
            "Salvaje: Rutas 3, 4, 22, 23 y Túnel Roca."
        ],
        "Diamante": [
            "Salvaje: Rutas 225 y 226 (Pokéradar).",
            "Parque Compi: Zona rocosa."
        ],
        "Perla": [
            "Salvaje: Rutas 225 y 226 (Pokéradar).",
            "Parque Compi: Zona rocosa."
        ],
        "Platino": [
            "Salvaje: Ruta 225 (Pokéradar).",
            "Parque Compi: Zona rocosa."
        ],
        "Oro HeartGold": [
            "Salvaje: Ruta 9 y Ruta 42.",
            "Parque Compi: Zona rocosa."
        ],
        "Plata SoulSilver": [
            "Intercambiar: de Pokémon Oro HeartGold.",
            "Parque Compi: Zona rocosa."
        ],
        "Negro": [
            "Manada Pokémon: Ruta 15.",
            "Dream World: Monte Escarpado."
        ],
        "Blanco": [
            "Manada Pokémon: Ruta 15.",
            "Dream World: Monte Escarpado."
        ],
        "Negro 2": [
            "Intercambio del videojuego, (solo si se es chica): por cualquier Pokémon con el dueño del objeto perdido en Ciudad Mayólica al llamarlo un cierto número de veces. Está al nivel 50, equipado con un carameloraro y tiene la habilidad competitivo."
        ],
        "Blanco 2": [
            "Intercambio del videojuego, (solo si se es chica): por cualquier Pokémon con el dueño del objeto perdido en Ciudad Mayólica al llamarlo un cierto número de veces. Está al nivel 50, equipado con un carameloraro y tiene la habilidad competitivo."
        ],
        "Pokémon X": [
            "Salvaje: Safari Amistad."
        ],
        "Pokémon Y": [
            "Salvaje: Safari Amistad."
        ],
        "Rubí Omega": [
            "Salvaje: Desfiladero, usando el DexNav después de tener la Pokédex Nacional"
        ],
        "Zafiro Alfa": [
            "Salvaje: Desfiladero, usando el DexNav después de tener la Pokédex Nacional"
        ],
        "Sol": [
            "Salvaje: Ruta 3."
        ],
        "Luna": [
            "Salvaje: Ruta 3."
        ],
        "Ultrasol": [
            "Salvaje: Ruta 3."
        ],
        "Ultraluna": [
            "Salvaje: Ruta 3."
        ],
        "Espada": [
            "Mankey no se puede conseguir en este videojuego."
        ],
        "Escudo": [
            "Mankey no se puede conseguir en este videojuego."
        ],
        "Diamante Brillante": [
            "PokéRadar: Rutas 225 y 226.",
            "Grutas del Subsuelo: Cueva Menor, Cueva Espaciosa, Cueva Herbazal, Cueva Pradera y Caverna Solana."
        ],
        "Perla Reluciente": [
            "PokéRadar: Rutas 225 y 226.",
            "Grutas del Subsuelo: Cueva Menor, Cueva Espaciosa, Cueva Herbazal, Cueva Pradera y Caverna Solana."
        ],
        "Leyendas: Arceus": [
            "Mankey no se puede conseguir en este videojuego."
        ]
    },
    "pokedex": {
        "RojoAzul": "Se enfada muy fácilmente. Puede pasar de la tranquilidad a la ira en apenas un segundo.",
        "Amarillo": "Este ágil Pokémon vive en los arboles. Se enfada fácilmente y no dudará en atacar a todos.",
        "Oro": "Tiene muy mal humor. Cuando se agrupan atacan a cualquier cosa sin motivo aparente.",
        "Plata": "Es peligroso acercarse si se enfada sin razón aparente, ya que no distingue entre amigos y enemigos.",
        "Cristal": "Vive en grupos en las copas de los árboles. Al alejarse de la manada se siente solo y se enfada.",
        "Rubí": "Cuando Mankey empieza a temblar y a respirar con más intensidad, seguro que va a enfadarse. Aunque prever su enfado no sirve de nada porque alcanza un estado de rabia tan rápido que no hay escapatoria.",
        "Zafiro": "Cuando Mankey empieza a temblar y a respirar con más intensidad, seguro que va a enfadarse. Aunque prever su enfado no sirve de nada porque alcanza un estado de rabia tan rápido que no hay escapatoria.",
        "Esmeralda": "Si empieza a temblar y a respirar de forma agitada es que va a enfadarse. Aunque prever su enfado es inútil pues llega tan rápido que no da tiempo de huir.",
        "Rojo Fuego": "Es muy ligero y ágil, y también violento. Cuando se enfada, no hay quien controle el estado de furia en el que entra.",
        "Verde Hoja": "Se enfada muy fácilmente. Puede pasar de la tranquilidad a la ira en apenas un segundo.",
        "Diamante": "Vive en colonias en los árboles. Si uno se enfada, el resto de la manada ataca sin motivo.",
        "Perla": "Vive en colonias en los árboles. Si uno se enfada, el resto de la manada ataca sin motivo.",
        "Platino": "Vive en colonias en los árboles. Si uno se enfada, el resto de la manada ataca sin motivo.",
        "Oro HeartGold": "Tiene muy mal humor. En grupo ataca cualquier cosa sin motivo",
        "Plata SoulSilver": "Es peligroso acercarse si se enfada sin razón aparente, ya que no distingue entre amigos y enemigos.",
        "Negro": "Vive en colonias en los árboles. Si uno se enfada, el resto de la manada ataca sin motivo.",
        "Blanco": "Vive en colonias en los árboles. Si uno se enfada, el resto de la manada ataca sin motivo.",
        "Negro 2": "Vive en colonias en los árboles. Si uno se enfada, el resto de la manada ataca sin motivo.",
        "Blanco 2": "Vive en colonias en los árboles. Si uno se enfada, el resto de la manada ataca sin motivo.",
        "Pokémon X": "Es peligroso acercarse si se enfada sin razón aparente, ya que no distingue entre amigos y enemigos.",
        "Pokémon Y": "Vive en colonias en los árboles. Si uno se enfada, el resto de la manada ataca sin motivo.",
        "Rubí Omega": "Cuando Mankey empieza a temblar y a respirar con más intensidad, seguro que va a enfadarse. Aunque prever su enfado no sirve de nada porque alcanza un estado de rabia tan rápido que no hay escapatoria.",
        "Zafiro Alfa": "Cuando Mankey empieza a temblar y a respirar con más intensidad, seguro que va a enfadarse. Aunque prever su enfado no sirve de nada porque alcanza un estado de rabia tan rápido que no hay escapatoria.",
        "Sol": "Se enfada sin razón aparente. Cuando todos lo dejan solo para no tener que lidiar con su ira, Mankey se enoja más aún.",
        "Luna": "Tras desatar su ira, le entra sueño y se duerme. Sin embargo, sus pesadillas lo atormentan aún más, por lo que se despierta de muy mal humor.",
        "Ultrasol": "Se encoleriza enseguida por cualquier minucia. Por otro lado, al no acumular estrés, suele gozar de una vida longeva.",
        "Ultraluna": "Cuando un ejemplar se enfada, contagia su ira al resto, por lo que los grupos de Mankey desconocen el concepto de vida reposada.",
        "Let's Go Pikachu!Let's Go Eevee!": "Este ágil Pokémon vive en los árboles. Se enfada con facilidad y, cuando lo hace, se abalanza contra todo lo que se encuentre a su alrededor.",
        "Espada": "Este Pokémon no se puede conseguir en Pokémon Espada.",
        "Escudo": "Este Pokémon no se puede conseguir en Pokémon Escudo.",
        "Diamante Brillante": "Vive en colonias en los árboles. Si uno se enfada, el resto de la manada se enfurece sin motivo.",
        "Perla Reluciente": "Vive en colonias en los árboles. Si uno se enfada, el resto de la manada se enfurece sin motivo.",
        "Leyendas: Arceus": "Este Pokémon no se puede conseguir en Leyendas Pokémon: Arceus."
    },
    "evolution": [
        [
            "Mankey",
            "Nivel 28",
            "Primeape"
        ]
    ]
}