{
    "dex number": "081",
    "pokemon name": "Magnemite",
    "types": [
        "eléctrico",
        "acero"
    ],
    "abilities": [
        "Imán (habilidad)",
        "Robustez"
    ],
    "hidden abilities": [
        "Cálculo final"
    ],
    "stats": {
        "hp": "25",
        "atk": "35",
        "def": "70",
        "atk esp": "95",
        "def esp": "55",
        "speed": "45"
    },
    "location": {
        "Rojo": [
            "Salvaje: Central de Energía"
        ],
        "Azul": [
            "Salvaje: Central de Energía"
        ],
        "Amarillo": [
            "Salvaje: Ruta 10 y Central de Energía"
        ],
        "Oro": [
            "Salvaje: Ruta 6, ruta 11, ruta 38 y ruta 39"
        ],
        "Plata": [
            "Salvaje: Ruta 6, ruta 11, ruta 38 y ruta 39"
        ],
        "Cristal": [
            "Salvaje: Ruta 6, ruta 11, ruta 38 y ruta 39"
        ],
        "Rubí": [
            "Salvaje: Malvalanova"
        ],
        "Zafiro": [
            "Salvaje: Malvalanova"
        ],
        "Esmeralda": [
            "Salvaje: Malvalanova"
        ],
        "Rojo Fuego": [
            "Salvaje: Central de Energía"
        ],
        "Verde Hoja": [
            "Salvaje: Central de Energía"
        ],
        "Diamante": [
            "Manada: Forja Fuego",
            "Parque Compi: Zona rocosa"
        ],
        "Perla": [
            "Manada: Forja Fuego",
            "Parque Compi: Zona rocosa"
        ],
        "Platino": [
            "Salvaje: Forja Fuego y ruta 222",
            "Parque Compi: Zona rocosa"
        ],
        "Oro HeartGold": [
            "Salvaje: Ruta 6, ruta 11, ruta 38, ruta 39 y Zona Safari (páramo y peña)",
            "Pokéwalker: Urbanización",
            "Parque Compi: Zona rocosa"
        ],
        "Plata SoulSilver": [
            "Salvaje: Ruta 6, ruta 11, ruta 38, ruta 39 y Zona Safari (páramo y peña)",
            "Pokéwalker: Urbanización",
            "Parque Compi: Zona rocosa"
        ],
        "Negro": [
            "Intercambiar: de Pokémon Blanco, Pokémon Negro 2 o Pokémon Blanco 2",
            "Dream World: Monte Escarpado"
        ],
        "Blanco": [
            "Salvaje: Bosque Blanco",
            "Dream World: Monte Escarpado"
        ],
        "Negro 2": [
            "Salvaje: Polígono Hormigón",
            "Dream World: Monte Escarpado"
        ],
        "Blanco 2": [
            "Salvaje: Polígono Hormigón",
            "Dream World: Monte Escarpado"
        ],
        "Pokémon X": [
            "Criar: de Magneton o de Magnezone"
        ],
        "Pokémon Y": [
            "Criar: de Magneton o de Magnezone"
        ],
        "Rubí Omega": [
            "Salvaje: Ruta 110 (encuentro de horda) y Malvalanova"
        ],
        "Zafiro Alfa": [
            "Salvaje: Ruta 110 (encuentro de horda) y Malvalanova"
        ],
        "Sol": [
            "Salvaje: Ciudad Hauoli, Escuela de entrenadores y Cabo de las Afueras",
            "Poké Resort: Cayo Recreo, tras llegar a Akala"
        ],
        "Luna": [
            "Salvaje: Ciudad Hauoli, Escuela de entrenadores y Cabo de las Afueras",
            "Poké Resort: Cayo Recreo, tras llegar a Akala"
        ],
        "Ultrasol": [
            "Salvaje: Ciudad Hauoli, Escuela de entrenadores y Cabo de las Afueras"
        ],
        "Ultraluna": [
            "Salvaje: Ciudad Hauoli, Escuela de entrenadores y Cabo de las Afueras"
        ],
        "Let's Go Pikachu!": [
            "Salvaje: Central de Energía"
        ],
        "Let's Go Eevee!": [
            "Salvaje: Central de Energía"
        ],
        "Espada": [
            "Salvaje: Playa Desafío ",
            "Incursiones Dinamax: nidos en Prado Reverencia , Bosque Concentración , Playa Desafío, Cueva Contienda , Cueva Tenacidad , Mar Andana  y Mar Meloso "
        ],
        "Escudo": [
            "Salvaje: Playa Desafío ",
            "Incursiones Dinamax: nidos en Prado Reverencia , Bosque Concentración , Playa Desafío, Cueva Contienda , Cueva Tenacidad , Mar Andana  y Mar Meloso "
        ],
        "Diamante Brillante": [
            "Manada: Forja Fuego.",
            "Grutas del Subsuelo: Cueva Menor, Cueva Espaciosa, Cueva Nevisca, Cueva Ventisca, Cueva Témpano, Cueva Carámbano y Caverna Glaciar."
        ],
        "Perla Reluciente": [
            "Manada: Forja Fuego.",
            "Grutas del Subsuelo: Cueva Menor, Cueva Espaciosa, Cueva Nevisca, Cueva Ventisca, Cueva Témpano, Cueva Carámbano y Caverna Glaciar."
        ],
        "Leyendas: Arceus": [
            "Salvaje: Distorsión espaciotemporal en Costa Cobalto."
        ]
    },
    "pokedex": {
        "RojoAzul": "Anula la gravedad para mantenerse en el aire. Sin previo aviso usa la ondatrueno y parecidos.",
        "Amarillo": "Puede desafiar a la gravedad desde su nacimiento. Flota en el aire gracias a ondas electromagnéticas.",
        "Oro": "Atraído por ondas electromagnéticas, podría acercarse a los entrenadores que estén usando el Pokégear.",
        "Plata": "Las unidades a los lados de su cuerpo generan energía antigravitatoria para mantenerlo en el aire.",
        "Cristal": "La gran cantidad de electricidad que libera por todos lados, le convierte en un potente imán.",
        "Rubí": "Magnemite se engancha a las líneas de tensión para nutrirse de electricidad. Si se produce un apagón en tu casa, mira el automático, no vaya a ser que haya un montón de estos Pokémon colgados de la caja de fusibles.",
        "Zafiro": "Magnemite flota en el aire emitiendo ondas electromagnéticas a través de las unidades de las extremidades, que bloquean la gravedad. Si se agota su suministro de electricidad interno, es incapaz de mantenerse flotando.",
        "Esmeralda": "Las unidades de las extremidades son imanes de largo alcance. Generan magnetismo suficiente para atraer objetos de hierro que estén a 100 m de distancia.",
        "Rojo Fuego": "Está suspendido en el aire y no para de moverse. A través de las extremidades laterales dispara onda trueno.",
        "Verde Hoja": "Anula la gravedad para mantenerse en el aire. Sin previo aviso usa onda trueno y parecidos.",
        "Diamante": "Las unidades laterales crean ondas electromagnéticas que le permiten flotar. Se alimenta de electricidad.",
        "Perla": "Las unidades laterales crean ondas electromagnéticas que le permiten flotar. Se alimenta de electricidad.",
        "Platino": "Cuanto más rápido rotan las unidades laterales, mayor fuerza magnética generan.",
        "Oro HeartGold": "Atraído por ondas electromagnéticas, podría acercarse a los entrenadores que estén usando el Pokégear.",
        "Plata SoulSilver": "Las unidades a los lados de su cuerpo generan energía antigravitatoria para mantenerlo en el aire.",
        "Negro": "Cuanto más rápido rotan las unidades laterales, mayor fuerza magnética generan.",
        "Blanco": "Cuanto más rápido rotan las unidades laterales, mayor fuerza magnética generan.",
        "Negro 2": "Las unidades laterales crean ondas electromagnéticas que contrarrestan la gravedad y le permiten flotar.",
        "Blanco 2": "Las unidades laterales crean ondas electromagnéticas que contrarrestan la gravedad y le permiten flotar.",
        "Pokémon X": "Las unidades a los lados de su cuerpo generan energía antigravitatoria para mantenerlo en el aire.",
        "Pokémon Y": "Está suspendido en el aire y no para de moverse. A través de las extremidades laterales dispara onda trueno.",
        "Rubí Omega": "Magnemite se engancha a las líneas de tensión para nutrirse de electricidad. Cuando se producen apagones en las casas, es aconsejable revisar el automático y comprobar que no hay Pokémon de este tipo colgados de la caja de fusibles.",
        "Zafiro Alfa": "Magnemite flota en el aire emitiendo ondas electromagnéticas a través de las unidades de las extremidades, que bloquean la gravedad. Si se agota su suministro de electricidad interno, es incapaz de mantenerse flotando.",
        "Sol": "Estos Pokémon se agrupan en zonas donde hay electricidad. A veces hasta se los ve merodeando alrededor de las torres eléctricas.",
        "Luna": "Flota gracias a las ondas electromagnéticas que desprende. Al tocarlo mientras está alimentándose, uno puede electrocutarse.",
        "Ultrasol": "Frecuentemente son la causa de apagones, por lo que algunas centrales eléctricas emiten unas ondas que detestan para ahuyentarlos.",
        "Ultraluna": "Debido a que el tendido eléctrico es ahora soterrado, han aumentado los asaltos a centrales eléctricas causados por Magnemite.",
        "Let's Go Pikachu!Let's Go Eevee!": "Puede desafiar la gravedad desde su nacimiento. Flota en el aire gracias a las ondas electromagnéticas que emite.",
        "Espada": "A veces se desploman al suelo tras agotar su suministro eléctrico interno, pero basta una pequeña batería para reanimarlos.",
        "Escudo": "Se nutre de electricidad. Puede flotar en el aire gracias a las ondas electromagnéticas que emite a través de las unidades de sus extremidades.",
        "Diamante Brillante": "Las unidades laterales crean ondas electromagnéticas que le permiten flotar. Se alimenta de electricidad.",
        "Perla Reluciente": "Las unidades laterales crean ondas electromagnéticas que le permiten flotar. Se alimenta de electricidad.",
        "Leyendas: Arceus": "Su aspecto de bola metálica con un ojo resulta verdaderamente extraño. Suponemos que flota gracias al magnetismo de los imanes con forma de herradura a ambos lados de su cuerpo.",
        "Stadium": "Aparece salido de ninguna parte. Flota utilizando anti-gravedad y descarga electricidad con sus dos unidades laterales.",
        "Stadium 2": "Pokémon Oro insertado:  Las unidades a los lados de su cuerpo generan energía antigravitatoria para mantenerlo en el aire.\nPokémon Plata insertado: Atraído por ondas electromagnéticas, podría acercarse a los entrenadores que estén usando el Pokégear.\n",
        "Pokémon GO": "Magnemite se engancha a las líneas de tensión para nutrirse de electricidad. Cuando se producen apagones en las casas, es aconsejable revisar el automático y comprobar que no hay Pokémon de este tipo colgados de la caja de fusibles.",
        "Ranger": "Magnemite libera electricidad para atacar. También puede recargar tu capturador.",
        "Sombras de Almia": "Ataca liberando descargas eléctricas.",
        "RubíZafiro": "Magnemite flota en el aire emitiendo ondas electromagnéticas a través de las unidades de las extremidades, que bloquean la gravedad. Si se agota su suministro de electricidad interno, es incapaz de mantenerse flotando."
    },
    "evolution": [
        [
            "Magnemite",
            "Nivel 30",
            "Magneton",
            "Subir un nivel en un campo magnético especial3;o piedra trueno4 ",
            "Magnezone"
        ]
    ]
}